odoo8_addon_product_profile_example-8.0.1.0.1.99.dev7-py2.7-nspkg.pth
odoo8_addon_product_profile_example-8.0.1.0.1.99.dev7.dist-info/DESCRIPTION.rst
odoo8_addon_product_profile_example-8.0.1.0.1.99.dev7.dist-info/METADATA
odoo8_addon_product_profile_example-8.0.1.0.1.99.dev7.dist-info/RECORD
odoo8_addon_product_profile_example-8.0.1.0.1.99.dev7.dist-info/WHEEL
odoo8_addon_product_profile_example-8.0.1.0.1.99.dev7.dist-info/metadata.json
odoo8_addon_product_profile_example-8.0.1.0.1.99.dev7.dist-info/namespace_packages.txt
odoo8_addon_product_profile_example-8.0.1.0.1.99.dev7.dist-info/top_level.txt
odoo_addons/product_profile_example/README.rst
odoo_addons/product_profile_example/__init__.py
odoo_addons/product_profile_example/__openerp__.py
odoo_addons/product_profile_example/product.profile.csv
odoo_addons/product_profile_example/product_product_demo.xml
odoo_addons/product_profile_example/profile.py
odoo_addons/product_profile_example/i18n/de.po
odoo_addons/product_profile_example/i18n/product_profile_example.pot
odoo_addons/product_profile_example/i18n/sl.po
odoo_addons/product_profile_example/static/description/akretion.png
odoo_addons/product_profile_example/static/description/field.png
odoo_addons/product_profile_example/static/description/icon.png
odoo_addons/product_profile_example/static/description/index.html
odoo_addons/product_profile_example/static/description/list.png
odoo_addons/product_profile_example/tests/__init__.py
odoo_addons/product_profile_example/tests/test_profile.py
