Metadata-Version: 2.0
Name: odoo8-addon-product-profile-example
Version: 8.0.1.0.1.99.dev7
Summary: Product Profile Use Case
Home-page: http://www.akretion.com/
Author: Akretion, Odoo Community Association (OCA)
Author-email: support@odoo-community.org
License: AGPL-3
Platform: UNKNOWN
Classifier: Programming Language :: Python
Classifier: Framework :: Odoo
Classifier: License :: OSI Approved :: GNU Affero General Public License v3
Requires-Python: ~=2.7
Requires-Dist: odoo (<9.0a,>=8.0a)
Requires-Dist: odoo8-addon-product-profile
